odoo/addons/product_main_supplierinfo/README.rst
odoo/addons/product_main_supplierinfo/__init__.py
odoo/addons/product_main_supplierinfo/__manifest__.py
odoo/addons/product_main_supplierinfo/i18n/es.po
odoo/addons/product_main_supplierinfo/i18n/fr.po
odoo/addons/product_main_supplierinfo/i18n/it.po
odoo/addons/product_main_supplierinfo/i18n/product_main_supplierinfo.pot
odoo/addons/product_main_supplierinfo/models/__init__.py
odoo/addons/product_main_supplierinfo/models/product_product.py
odoo/addons/product_main_supplierinfo/readme/CONTRIBUTORS.rst
odoo/addons/product_main_supplierinfo/readme/DESCRIPTION.rst
odoo/addons/product_main_supplierinfo/static/description/icon.png
odoo/addons/product_main_supplierinfo/static/description/index.html
odoo/addons/product_main_supplierinfo/tests/__init__.py
odoo/addons/product_main_supplierinfo/tests/test_product_main_supplier.py
odoo/addons/product_main_supplierinfo/views/product_product.xml
odoo14_addon_product_main_supplierinfo-14.0.1.0.2.dist-info/METADATA
odoo14_addon_product_main_supplierinfo-14.0.1.0.2.dist-info/WHEEL
odoo14_addon_product_main_supplierinfo-14.0.1.0.2.dist-info/top_level.txt
odoo14_addon_product_main_supplierinfo-14.0.1.0.2.dist-info/RECORD
